<?xml version="1.0" encoding="UTF-8"?><record_update>
    <sys_choice action="INSERT_OR_UPDATE" field="breed" table="x_1320315_fetch_dogs" version="3">
        <sys_choice_set action="INSERT_OR_UPDATE">
            <element>breed</element>
            <name>x_1320315_fetch_dogs</name>
            <sys_class_name>sys_choice_set</sys_class_name>
            <sys_created_by>admin</sys_created_by>
            <sys_created_on>2024-03-13 15:50:08</sys_created_on>
            <sys_mod_count>0</sys_mod_count>
            <sys_name>breed</sys_name>
            <sys_package display_value="Fetch" source="x_1320315_fetch">ed66a52b97f00a500606bed0f053afd9</sys_package>
            <sys_policy/>
            <sys_scope display_value="Fetch">ed66a52b97f00a500606bed0f053afd9</sys_scope>
            <sys_update_name>sys_choice_x_1320315_fetch_dogs_breed</sys_update_name>
            <sys_updated_by>admin</sys_updated_by>
            <sys_updated_on>2024-03-13 15:50:08</sys_updated_on>
        </sys_choice_set>
        <sys_choice action="INSERT_OR_UPDATE">
            <dependent_value/>
            <element>breed</element>
            <hint/>
            <inactive>false</inactive>
            <label>German Shephared</label>
            <language>en</language>
            <name>x_1320315_fetch_dogs</name>
            <sequence/>
            <synonyms/>
            <sys_created_by>admin</sys_created_by>
            <sys_created_on>2024-03-13 15:52:22</sys_created_on>
            <sys_domain>global</sys_domain>
            <sys_domain_path>/</sys_domain_path>
            <sys_mod_count>0</sys_mod_count>
            <sys_updated_by>admin</sys_updated_by>
            <sys_updated_on>2024-03-13 15:52:22</sys_updated_on>
            <value>german_shephared</value>
        </sys_choice>
        <sys_choice action="INSERT_OR_UPDATE">
            <dependent_value/>
            <element>breed</element>
            <hint/>
            <inactive>false</inactive>
            <label>Labrador</label>
            <language>en</language>
            <name>x_1320315_fetch_dogs</name>
            <sequence>0</sequence>
            <synonyms/>
            <sys_created_by>admin</sys_created_by>
            <sys_created_on>2024-03-13 15:50:08</sys_created_on>
            <sys_domain>global</sys_domain>
            <sys_domain_path>/</sys_domain_path>
            <sys_mod_count>0</sys_mod_count>
            <sys_updated_by>admin</sys_updated_by>
            <sys_updated_on>2024-03-13 15:50:08</sys_updated_on>
            <value>labrador</value>
        </sys_choice>
        <sys_choice action="INSERT_OR_UPDATE">
            <dependent_value/>
            <element>breed</element>
            <hint/>
            <inactive>false</inactive>
            <label>Mix</label>
            <language>en</language>
            <name>x_1320315_fetch_dogs</name>
            <sequence>2</sequence>
            <synonyms/>
            <sys_created_by>admin</sys_created_by>
            <sys_created_on>2024-03-13 15:50:41</sys_created_on>
            <sys_domain>global</sys_domain>
            <sys_domain_path>/</sys_domain_path>
            <sys_mod_count>1</sys_mod_count>
            <sys_updated_by>admin</sys_updated_by>
            <sys_updated_on>2024-03-13 15:51:06</sys_updated_on>
            <value>mix</value>
        </sys_choice>
    </sys_choice>
</record_update>
